inkyphat-1.0.1.dist-info/metadata.json
inkyphat-1.0.1.dist-info/WHEEL
inkyphat-1.0.1.dist-info/METADATA
inkyphat-1.0.1.dist-info/DESCRIPTION.rst
inkyphat-1.0.1.dist-info/top_level.txt
inkyphat-1.0.1.dist-info/RECORD
inkyphat/__init__.py
inkyphat/inky212x104.py
inkyphat/fonts/__init__.py
inkyphat/fonts/OFL.txt
inkyphat/fonts/AmaticSC-Bold.ttf
inkyphat/fonts/AmaticSC-Regular.ttf
inkyphat/fonts/FredokaOne-Regular.ttf
inkyphat/fonts/PressStart2P-Regular.ttf
